crystallize_extras/__init__.py
crystallize_extras/ollama_step/__init__.py
crystallize_extras/ollama_step/initialize.py
crystallize_extras/ollama_step/initialize_async.py
crystallize_extras/openai_step/__init__.py
crystallize_extras/openai_step/initialize.py
crystallize_extras/openai_step/initialize_async.py
crystallize_extras/ray_plugin/__init__.py
crystallize_extras/ray_plugin/execution.py
crystallize_extras/vllm_step/__init__.py
crystallize_extras/vllm_step/initialize.py
crystallize_extras-0.7.3.dist-info/METADATA
crystallize_extras-0.7.3.dist-info/WHEEL
crystallize_extras-0.7.3.dist-info/top_level.txt
crystallize_extras-0.7.3.dist-info/RECORD
