Metadata-Version: 2.4
Name: crystallize-extras
Version: 0.7.3
Summary: Optional plugins and components for the Crystallize framework.
Requires-Python: >=3.10
Requires-Dist: crystallize-ml
Provides-Extra: ray
Requires-Dist: ray; extra == "ray"
Provides-Extra: vllm
Requires-Dist: vllm; extra == "vllm"
Provides-Extra: ollama
Requires-Dist: ollama; extra == "ollama"
Provides-Extra: openai
Requires-Dist: openai; extra == "openai"
